sonicbit/__init__.py
sonicbit/base.py
sonicbit/client.py
sonicbit/constants.py
sonicbit/enums.py
sonicbit/errors.py
sonicbit/utils.py
sonicbit/handlers/__init__.py
sonicbit/handlers/token_file_handler.py
sonicbit/handlers/token_handler.py
sonicbit/modules/__init__.py
sonicbit/modules/auth.py
sonicbit/modules/file.py
sonicbit/modules/remote_download.py
sonicbit/modules/signup.py
sonicbit/modules/torrent.py
sonicbit/modules/user.py
sonicbit/types/__init__.py
sonicbit/types/app.py
sonicbit/types/auth_response.py
sonicbit/types/file.py
sonicbit/types/file_list.py
sonicbit/types/path_info.py
sonicbit/types/storage_details.py
sonicbit/types/user_details.py
sonicbit/types/remote_download/__init__.py
sonicbit/types/remote_download/remote_task.py
sonicbit/types/remote_download/remote_task_list.py
sonicbit/types/torrent/__init__.py
sonicbit/types/torrent/torrent.py
sonicbit/types/torrent/torrent_details.py
sonicbit/types/torrent/torrent_file.py
sonicbit/types/torrent/torrent_info.py
sonicbit/types/torrent/torrent_list.py
sonicbit-0.2.2.dist-info/LICENSE
sonicbit-0.2.2.dist-info/METADATA
sonicbit-0.2.2.dist-info/WHEEL
sonicbit-0.2.2.dist-info/top_level.txt
sonicbit-0.2.2.dist-info/RECORD
