Metadata-Version: 2.1
Name: sonicbit
Version: 0.2.2
Summary: An unofficial Python SDK for SonicBit which uses the internal API to interact with the application.
Home-page: https://github.com/viperadnan-git/sonicbit-python-sdk
Author: Adnan Ahmad
Author-email: viperadnan@gmail.com
License: GNU General Public License v3.0
Keywords: sonicbit python sdk
Classifier: Programming Language :: Python :: 3
Classifier: License :: OSI Approved :: GNU General Public License v3 (GPLv3)
Classifier: Operating System :: OS Independent
Requires-Python: >=3.10
License-File: LICENSE
Requires-Dist: requests
